postman_api_fetcher/__init__.py
postman_api_fetcher/postman_api_fetcher.py
postman_api_fetcher-0.1.0.dist-info/METADATA
postman_api_fetcher-0.1.0.dist-info/WHEEL
postman_api_fetcher-0.1.0.dist-info/top_level.txt
postman_api_fetcher-0.1.0.dist-info/RECORD
