Metadata-Version: 2.1
Name: postman-api-fetcher
Version: 0.1.0
Summary: A simple Postman API fetcher
Home-page: 
Author: M Samarth Mahendra
Author-email: samarth.mahendragowda@gmail.com
Requires-Dist: requests
